[
	{
		
		"Title": "Write a report",
		"IsDone": false,
		"Periodicity": 1,
		"TaskPriority": 1,
		"TaskCategory": 2
	},
	{
		"Title": "Do lab work",
		"TaskDescription": "",
		"IsDone": false,
		"Periodicity": 1,
		"TaskPriority": 1,
		"TaskCategory": 1
	},
	{
		"Title": "Wash the floor",
		"TaskDescription": "",
		"IsDone": false,
		"Periodicity": 1,
		"TaskPriority": 2,
		"TaskCategory": 3
	},
	{
		"Title": "Walk the dog",
		"TaskDescription": "",
		"IsDone": false,
		"Periodicity": 1,
		"TaskPriority": 3,
		"TaskCategory": 4
	}
]